sqlalchemy_mongobi/__init__.py
sqlalchemy_mongobi/dialect.py
sqlalchemy_mongobi-0.2.1.dist-info/DESCRIPTION.rst
sqlalchemy_mongobi-0.2.1.dist-info/METADATA
sqlalchemy_mongobi-0.2.1.dist-info/RECORD
sqlalchemy_mongobi-0.2.1.dist-info/WHEEL
sqlalchemy_mongobi-0.2.1.dist-info/entry_points.txt
sqlalchemy_mongobi-0.2.1.dist-info/metadata.json
sqlalchemy_mongobi-0.2.1.dist-info/top_level.txt
