Metadata-Version: 2.0
Name: sqlalchemy-mongobi
Version: 0.2.1
Summary: MongoDB connector for BI SQLAlchemy Dialect
Home-page: https://github.com/smarzola/sqlalchemy-mongobi
Author: Simone Marzola
Author-email: marzolasimone@gmail.com
License: MIT license
Keywords: sqlalchemy mongodb
Platform: UNKNOWN
Classifier: Development Status :: 4 - Beta
Classifier: Intended Audience :: Developers
Classifier: License :: OSI Approved :: MIT License
Classifier: Natural Language :: English
Classifier: Programming Language :: Python :: 3
Classifier: Programming Language :: Python :: 3.4
Classifier: Programming Language :: Python :: 3.5
Classifier: Programming Language :: Python :: 3.6
Classifier: Programming Language :: Python :: 3.7
Requires-Dist: sqlalchemy
